setup.py
src/__init__.py
src/log.py
src/xkcdHermit.py
xkcdhermit.egg-info/PKG-INFO
xkcdhermit.egg-info/SOURCES.txt
xkcdhermit.egg-info/dependency_links.txt
xkcdhermit.egg-info/entry_points.txt
xkcdhermit.egg-info/requires.txt
xkcdhermit.egg-info/top_level.txt