Metadata-Version: 1.0
Name: xkcdhermit
Version: 0.0.1
Summary: xkcdhermit replies to everything with an xkcd comic.
Home-page: http://github.com/lakshaykalbhor/xkcdhermit
Author: Lakshay Kalbhor
Author-email: lakshaykalbhor@gmail.com
License: MIT
Keywords: xkcd,git,github,command line,cli,hermit
Platform: UNKNOWN
